{
  "recordData": [
    {
      "id": 1,
      "update": "2021-12-17T21:16:38.847Z",
      "data": [
        {
          "id": 1,
          "timestamp": 1639639519000,
          "expectedStock": 15,
          "realStock": 10,
          "orders": [
            {
              "id": 1,
              "compagny": "officeDepot",
              "value": 5
            },
            {
              "id": 2,
              "compagny": "mailChimp",
              "value": 3
            },
            {
              "id": 3,
              "compagny": "aliExpress",
              "value": 2
            },
            {
              "id": 4,
              "compagny": "delphiTools",
              "value": 7
            }
          ]
        },
        {
          "id": 2,
          "timestamp": 1639725919000,
          "expectedStock": 13,
          "realStock": 12,
          "orders": [
            {
              "id": 1,
              "compagny": "ikea",
              "value": 5
            },
            {
              "id": 2,
              "compagny": "mailChimp",
              "value": 3
            },
            {
              "id": 3,
              "compagny": "aliExpress",
              "value": 4
            }
          ]
        },
        {
          "id": 3,
          "timestamp": 1639639519000,
          "expectedStock": 15,
          "realStock": 10,
          "orders": [
            {
              "id": 1,
              "compagny": "officeDepot",
              "value": 5
            },
            {
              "id": 2,
              "compagny": "officeDepot",
              "value": 5
            },
            {
              "id": 3,
              "compagny": "officeDepot",
              "value": 5
            },
            {
              "id": 4,
              "compagny": "mailChimp",
              "value": 3
            },
            {
              "id": 5,
              "compagny": "aliExpress",
              "value": 2
            },
            {
              "id": 6,
              "compagny": "delphiTools",
              "value": 7
            }
          ]
        },
        {
          "id": 4,
          "timestamp": 1639856376000,
          "expectedStock": 13,
          "realStock": 12,
          "orders": [
            {
              "id": 1,
              "compagny": "ikea",
              "value": 5
            }
          ]
        },
        {
          "id": 5,
          "timestamp": 1639639519000,
          "expectedStock": 15,
          "realStock": 10,
          "orders": [
            {
              "id": 1,
              "compagny": "officeDepot",
              "value": 5
            },
            {
              "id": 2,
              "compagny": "mailChimp",
              "value": 3
            },
            {
              "id": 3,
              "compagny": "aliExpress",
              "value": 2
            },
            {
              "id": 4,
              "compagny": "delphiTools",
              "value": 7
            }
          ]
        },
        {
          "id": 6,
          "timestamp": 1639725919000,
          "expectedStock": 13,
          "realStock": 12,
          "orders": [
            {
              "id": 1,
              "compagny": "ikea",
              "value": 5
            },
            {
              "id": 2,
              "compagny": "mailChimp",
              "value": 3
            },
            {
              "id": 3,
              "compagny": "aliExpress",
              "value": 4
            }
          ]
        },
        {
          "id": 7,
          "timestamp": 1639639519000,
          "expectedStock": 15,
          "realStock": 10,
          "orders": [
            {
              "id": 1,
              "compagny": "officeDepot",
              "value": 5
            },
            {
              "id": 2,
              "compagny": "officeDepot",
              "value": 5
            },
            {
              "id": 3,
              "compagny": "officeDepot",
              "value": 5
            },
            {
              "id": 4,
              "compagny": "mailChimp",
              "value": 3
            },
            {
              "id": 5,
              "compagny": "aliExpress",
              "value": 2
            },
            {
              "id": 6,
              "compagny": "delphiTools",
              "value": 7
            }
          ]
        },
        {
          "id": 8,
          "timestamp": 1639856376000,
          "expectedStock": 13,
          "realStock": 12,
          "orders": [
            {
              "id": 1,
              "compagny": "ikea",
              "value": 5
            }
          ]
        },
        {
          "id": 9,
          "timestamp": 1639639519000,
          "expectedStock": 15,
          "realStock": 10,
          "orders": [
            {
              "id": 1,
              "compagny": "officeDepot",
              "value": 5
            },
            {
              "id": 2,
              "compagny": "mailChimp",
              "value": 3
            },
            {
              "id": 3,
              "compagny": "aliExpress",
              "value": 2
            },
            {
              "id": 4,
              "compagny": "delphiTools",
              "value": 7
            }
          ]
        },
        {
          "id": 10,
          "timestamp": 1639725919000,
          "expectedStock": 13,
          "realStock": 12,
          "orders": [
            {
              "id": 1,
              "compagny": "ikea",
              "value": 5
            },
            {
              "id": 2,
              "compagny": "mailChimp",
              "value": 3
            },
            {
              "id": 3,
              "compagny": "aliExpress",
              "value": 4
            }
          ]
        },
        {
          "id": 11,
          "timestamp": 1639639519000,
          "expectedStock": 15,
          "realStock": 10,
          "orders": [
            {
              "id": 1,
              "compagny": "officeDepot",
              "value": 5
            },
            {
              "id": 2,
              "compagny": "officeDepot",
              "value": 5
            },
            {
              "id": 3,
              "compagny": "officeDepot",
              "value": 5
            },
            {
              "id": 4,
              "compagny": "mailChimp",
              "value": 3
            },
            {
              "id": 5,
              "compagny": "aliExpress",
              "value": 2
            },
            {
              "id": 6,
              "compagny": "delphiTools",
              "value": 7
            }
          ]
        },
        {
          "id": 12,
          "timestamp": 1639856376000,
          "expectedStock": 13,
          "realStock": 12,
          "orders": [
            {
              "id": 1,
              "compagny": "ikea",
              "value": 5
            }
          ]
        }
      ]
    },
    {
      "update": "2021-12-18T19:51:18.772Z",
      "data": [
        {
          "id": 1,
          "timestamp": 1639639519000,
          "expectedStock": 15,
          "realStock": 17,
          "orders": [
            {
              "id": 1,
              "compagny": "officeDepot",
              "value": 5
            },
            {
              "id": 2,
              "compagny": "mailChimp",
              "value": 3
            },
            {
              "id": 3,
              "compagny": "aliExpress",
              "value": 2
            },
            {
              "id": 4,
              "compagny": "delphiTools",
              "value": 7
            }
          ]
        },
        {
          "id": 2,
          "timestamp": 1639725919000,
          "expectedStock": 13,
          "realStock": 21,
          "orders": [
            {
              "id": 1,
              "compagny": "ikea",
              "value": 5
            },
            {
              "id": 2,
              "compagny": "mailChimp",
              "value": 3
            },
            {
              "id": 3,
              "compagny": "aliExpress",
              "value": 7
            },
            {
              "id": 3,
              "compagny": "HelloProvid",
              "value": 6
            }
          ]
        },
        {
          "id": 3,
          "timestamp": 1639639519000,
          "expectedStock": 15,
          "realStock": 27,
          "orders": [
            {
              "id": 1,
              "compagny": "officeDepot",
              "value": 5
            },
            {
              "id": 2,
              "compagny": "officeDepot",
              "value": 5
            },
            {
              "id": 3,
              "compagny": "officeDepot",
              "value": 5
            },
            {
              "id": 4,
              "compagny": "mailChimp",
              "value": 3
            },
            {
              "id": 5,
              "compagny": "aliExpress",
              "value": 2
            },
            {
              "id": 6,
              "compagny": "delphiTools",
              "value": 7
            }
          ]
        },
        {
          "id": 4,
          "timestamp": 1639856376000,
          "expectedStock": 13,
          "realStock": 5,
          "orders": [
            {
              "id": 1,
              "compagny": "ikea",
              "value": 5
            }
          ]
        },
        {
          "id": 5,
          "timestamp": 1639639519000,
          "expectedStock": 15,
          "realStock": 17,
          "orders": [
            {
              "id": 1,
              "compagny": "officeDepot",
              "value": 5
            },
            {
              "id": 2,
              "compagny": "mailChimp",
              "value": 3
            },
            {
              "id": 3,
              "compagny": "aliExpress",
              "value": 2
            },
            {
              "id": 4,
              "compagny": "delphiTools",
              "value": 7
            }
          ]
        },
        {
          "id": 6,
          "timestamp": 1639725919000,
          "expectedStock": 13,
          "realStock": 12,
          "orders": [
            {
              "id": 1,
              "compagny": "ikea",
              "value": 5
            },
            {
              "id": 2,
              "compagny": "mailChimp",
              "value": 3
            },
            {
              "id": 3,
              "compagny": "aliExpress",
              "value": 4
            }
          ]
        },
        {
          "id": 7,
          "timestamp": 1639639519000,
          "expectedStock": 15,
          "realStock": 27,
          "orders": [
            {
              "id": 1,
              "compagny": "officeDepot",
              "value": 5
            },
            {
              "id": 2,
              "compagny": "officeDepot",
              "value": 5
            },
            {
              "id": 3,
              "compagny": "officeDepot",
              "value": 5
            },
            {
              "id": 4,
              "compagny": "mailChimp",
              "value": 3
            },
            {
              "id": 5,
              "compagny": "aliExpress",
              "value": 2
            },
            {
              "id": 6,
              "compagny": "delphiTools",
              "value": 7
            }
          ]
        },
        {
          "id": 8,
          "timestamp": 1639856376000,
          "expectedStock": 13,
          "realStock": 5,
          "orders": [
            {
              "id": 1,
              "compagny": "ikea",
              "value": 5
            }
          ]
        },
        {
          "id": 9,
          "timestamp": 1639639519000,
          "expectedStock": 15,
          "realStock": 17,
          "orders": [
            {
              "id": 1,
              "compagny": "officeDepot",
              "value": 5
            },
            {
              "id": 2,
              "compagny": "mailChimp",
              "value": 3
            },
            {
              "id": 3,
              "compagny": "aliExpress",
              "value": 2
            },
            {
              "id": 4,
              "compagny": "delphiTools",
              "value": 7
            }
          ]
        },
        {
          "id": 10,
          "timestamp": 1639725919000,
          "expectedStock": 13,
          "realStock": 12,
          "orders": [
            {
              "id": 1,
              "compagny": "ikea",
              "value": 5
            },
            {
              "id": 2,
              "compagny": "mailChimp",
              "value": 3
            },
            {
              "id": 3,
              "compagny": "aliExpress",
              "value": 4
            }
          ]
        },
        {
          "id": 11,
          "timestamp": 1639639519000,
          "expectedStock": 15,
          "realStock": 27,
          "orders": [
            {
              "id": 1,
              "compagny": "officeDepot",
              "value": 5
            },
            {
              "id": 2,
              "compagny": "officeDepot",
              "value": 5
            },
            {
              "id": 3,
              "compagny": "officeDepot",
              "value": 5
            },
            {
              "id": 4,
              "compagny": "mailChimp",
              "value": 3
            },
            {
              "id": 5,
              "compagny": "aliExpress",
              "value": 2
            },
            {
              "id": 6,
              "compagny": "delphiTools",
              "value": 7
            }
          ]
        },
        {
          "id": 12,
          "timestamp": 1639856376000,
          "expectedStock": 13,
          "realStock": 5,
          "orders": [
            {
              "id": 1,
              "compagny": "ikea",
              "value": 5
            }
          ]
        }
      ],
      "id": 2
    },
    {
      "update": "2021-12-18T21:21:25.609Z",
      "data": [
        {
          "id": 1,
          "timestamp": 1639639519000,
          "expectedStock": 15,
          "realStock": 17,
          "orders": [
            {
              "id": 1,
              "compagny": "officeDepot",
              "value": 5
            },
            {
              "id": 2,
              "compagny": "mailChimp",
              "value": 3
            },
            {
              "id": 3,
              "compagny": "aliExpress",
              "value": 2
            },
            {
              "id": 4,
              "compagny": "delphiTools",
              "value": 7
            }
          ]
        },
        {
          "id": 2,
          "timestamp": 1639725919000,
          "expectedStock": 13,
          "realStock": 45,
          "orders": [
            {
              "id": 1,
              "compagny": "paper",
              "value": 5
            },
            {
              "id": 2,
              "compagny": "blue pens",
              "value": 5
            },
            {
              "id": 3,
              "compagny": "stapler",
              "value": 22
            },
            {
              "id": 3,
              "compagny": "post its",
              "value": 6
            },
            {
              "id": 4,
              "compagny": "calculator",
              "value": 7
            }
          ]
        },
        {
          "id": 3,
          "timestamp": 1639639519000,
          "expectedStock": 15,
          "realStock": 27,
          "orders": [
            {
              "id": 1,
              "compagny": "officeDepot",
              "value": 5
            },
            {
              "id": 2,
              "compagny": "officeDepot",
              "value": 5
            },
            {
              "id": 3,
              "compagny": "officeDepot",
              "value": 5
            },
            {
              "id": 4,
              "compagny": "mailChimp",
              "value": 3
            },
            {
              "id": 5,
              "compagny": "aliExpress",
              "value": 2
            },
            {
              "id": 6,
              "compagny": "delphiTools",
              "value": 7
            }
          ]
        },
        {
          "id": 4,
          "timestamp": 1639856376000,
          "expectedStock": 13,
          "realStock": 5,
          "orders": [
            {
              "id": 1,
              "compagny": "ikea",
              "value": 5
            }
          ]
        },
        {
          "id": 5,
          "timestamp": 1639639519000,
          "expectedStock": 15,
          "realStock": 17,
          "orders": [
            {
              "id": 1,
              "compagny": "officeDepot",
              "value": 5
            },
            {
              "id": 2,
              "compagny": "mailChimp",
              "value": 3
            },
            {
              "id": 3,
              "compagny": "aliExpress",
              "value": 2
            },
            {
              "id": 4,
              "compagny": "delphiTools",
              "value": 7
            }
          ]
        },
        {
          "id": 6,
          "timestamp": 1639725919000,
          "expectedStock": 13,
          "realStock": 12,
          "orders": [
            {
              "id": 1,
              "compagny": "ikea",
              "value": 5
            },
            {
              "id": 2,
              "compagny": "mailChimp",
              "value": 3
            },
            {
              "id": 3,
              "compagny": "aliExpress",
              "value": 4
            }
          ]
        },
        {
          "id": 7,
          "timestamp": 1639639519000,
          "expectedStock": 15,
          "realStock": 27,
          "orders": [
            {
              "id": 1,
              "compagny": "officeDepot",
              "value": 5
            },
            {
              "id": 2,
              "compagny": "officeDepot",
              "value": 5
            },
            {
              "id": 3,
              "compagny": "officeDepot",
              "value": 5
            },
            {
              "id": 4,
              "compagny": "mailChimp",
              "value": 3
            },
            {
              "id": 5,
              "compagny": "aliExpress",
              "value": 2
            },
            {
              "id": 6,
              "compagny": "delphiTools",
              "value": 7
            }
          ]
        },
        {
          "id": 8,
          "timestamp": 1639856376000,
          "expectedStock": 13,
          "realStock": 5,
          "orders": [
            {
              "id": 1,
              "compagny": "ikea",
              "value": 5
            }
          ]
        },
        {
          "id": 9,
          "timestamp": 1639639519000,
          "expectedStock": 15,
          "realStock": 17,
          "orders": [
            {
              "id": 1,
              "compagny": "officeDepot",
              "value": 5
            },
            {
              "id": 2,
              "compagny": "mailChimp",
              "value": 3
            },
            {
              "id": 3,
              "compagny": "aliExpress",
              "value": 2
            },
            {
              "id": 4,
              "compagny": "delphiTools",
              "value": 7
            }
          ]
        },
        {
          "id": 10,
          "timestamp": 1639725919000,
          "expectedStock": 13,
          "realStock": 12,
          "orders": [
            {
              "id": 1,
              "compagny": "ikea",
              "value": 5
            },
            {
              "id": 2,
              "compagny": "mailChimp",
              "value": 3
            },
            {
              "id": 3,
              "compagny": "aliExpress",
              "value": 4
            }
          ]
        },
        {
          "id": 11,
          "timestamp": 1639639519000,
          "expectedStock": 15,
          "realStock": 27,
          "orders": [
            {
              "id": 1,
              "compagny": "officeDepot",
              "value": 5
            },
            {
              "id": 2,
              "compagny": "officeDepot",
              "value": 5
            },
            {
              "id": 3,
              "compagny": "officeDepot",
              "value": 5
            },
            {
              "id": 4,
              "compagny": "mailChimp",
              "value": 3
            },
            {
              "id": 5,
              "compagny": "aliExpress",
              "value": 2
            },
            {
              "id": 6,
              "compagny": "delphiTools",
              "value": 7
            }
          ]
        },
        {
          "id": 12,
          "timestamp": 1639856376000,
          "expectedStock": 13,
          "realStock": 5,
          "orders": [
            {
              "id": 1,
              "compagny": "ikea",
              "value": 5
            }
          ]
        }
      ],
      "id": 3
    },
    {
      "update": "2021-12-18T21:43:19.777Z",
      "data": [
        {
          "id": 1,
          "timestamp": 1639639519000,
          "expectedStock": 150,
          "realStock": 17,
          "orders": [
            {
              "id": 1,
              "compagny": "officeDepot",
              "value": 5
            },
            {
              "id": 2,
              "compagny": "mailChimp",
              "value": 3
            },
            {
              "id": 3,
              "compagny": "aliExpress",
              "value": 2
            },
            {
              "id": 4,
              "compagny": "delphiTools",
              "value": 7
            }
          ]
        },
        {
          "id": 2,
          "timestamp": 1639725919000,
          "expectedStock": 13,
          "realStock": 45,
          "orders": [
            {
              "id": 1,
              "compagny": "paper",
              "value": 5
            },
            {
              "id": 2,
              "compagny": "blue pens",
              "value": 5
            },
            {
              "id": 3,
              "compagny": "stapler",
              "value": 22
            },
            {
              "id": 3,
              "compagny": "post its",
              "value": 6
            },
            {
              "id": 4,
              "compagny": "calculator",
              "value": 7
            }
          ]
        },
        {
          "id": 3,
          "timestamp": 1639639519000,
          "expectedStock": 15,
          "realStock": 27,
          "orders": [
            {
              "id": 1,
              "compagny": "officeDepot",
              "value": 5
            },
            {
              "id": 2,
              "compagny": "officeDepot",
              "value": 5
            },
            {
              "id": 3,
              "compagny": "officeDepot",
              "value": 5
            },
            {
              "id": 4,
              "compagny": "mailChimp",
              "value": 3
            },
            {
              "id": 5,
              "compagny": "aliExpress",
              "value": 2
            },
            {
              "id": 6,
              "compagny": "delphiTools",
              "value": 7
            }
          ]
        },
        {
          "id": 4,
          "timestamp": 1639856376000,
          "expectedStock": 13,
          "realStock": 5,
          "orders": [
            {
              "id": 1,
              "compagny": "ikea",
              "value": 5
            }
          ]
        },
        {
          "id": 5,
          "timestamp": 1639639519000,
          "expectedStock": 15,
          "realStock": 17,
          "orders": [
            {
              "id": 1,
              "compagny": "officeDepot",
              "value": 5
            },
            {
              "id": 2,
              "compagny": "mailChimp",
              "value": 3
            },
            {
              "id": 3,
              "compagny": "aliExpress",
              "value": 2
            },
            {
              "id": 4,
              "compagny": "delphiTools",
              "value": 7
            }
          ]
        },
        {
          "id": 6,
          "timestamp": 1639725919000,
          "expectedStock": 13,
          "realStock": 12,
          "orders": [
            {
              "id": 1,
              "compagny": "ikea",
              "value": 5
            },
            {
              "id": 2,
              "compagny": "mailChimp",
              "value": 3
            },
            {
              "id": 3,
              "compagny": "aliExpress",
              "value": 4
            }
          ]
        },
        {
          "id": 7,
          "timestamp": 1639639519000,
          "expectedStock": 15,
          "realStock": 27,
          "orders": [
            {
              "id": 1,
              "compagny": "officeDepot",
              "value": 5
            },
            {
              "id": 2,
              "compagny": "officeDepot",
              "value": 5
            },
            {
              "id": 3,
              "compagny": "officeDepot",
              "value": 5
            },
            {
              "id": 4,
              "compagny": "mailChimp",
              "value": 3
            },
            {
              "id": 5,
              "compagny": "aliExpress",
              "value": 2
            },
            {
              "id": 6,
              "compagny": "delphiTools",
              "value": 7
            }
          ]
        },
        {
          "id": 8,
          "timestamp": 1639856376000,
          "expectedStock": 13,
          "realStock": 5,
          "orders": [
            {
              "id": 1,
              "compagny": "ikea",
              "value": 5
            }
          ]
        },
        {
          "id": 9,
          "timestamp": 1639639519000,
          "expectedStock": 15,
          "realStock": 17,
          "orders": [
            {
              "id": 1,
              "compagny": "officeDepot",
              "value": 5
            },
            {
              "id": 2,
              "compagny": "mailChimp",
              "value": 3
            },
            {
              "id": 3,
              "compagny": "aliExpress",
              "value": 2
            },
            {
              "id": 4,
              "compagny": "delphiTools",
              "value": 7
            }
          ]
        },
        {
          "id": 10,
          "timestamp": 1639725919000,
          "expectedStock": 13,
          "realStock": 12,
          "orders": [
            {
              "id": 1,
              "compagny": "ikea",
              "value": 5
            },
            {
              "id": 2,
              "compagny": "mailChimp",
              "value": 3
            },
            {
              "id": 3,
              "compagny": "aliExpress",
              "value": 4
            }
          ]
        },
        {
          "id": 11,
          "timestamp": 1639639519000,
          "expectedStock": 15,
          "realStock": 27,
          "orders": [
            {
              "id": 1,
              "compagny": "officeDepot",
              "value": 5
            },
            {
              "id": 2,
              "compagny": "officeDepot",
              "value": 5
            },
            {
              "id": 3,
              "compagny": "officeDepot",
              "value": 5
            },
            {
              "id": 4,
              "compagny": "mailChimp",
              "value": 3
            },
            {
              "id": 5,
              "compagny": "aliExpress",
              "value": 2
            },
            {
              "id": 6,
              "compagny": "delphiTools",
              "value": 7
            }
          ]
        },
        {
          "id": 12,
          "timestamp": 1639856376000,
          "expectedStock": 13,
          "realStock": 5,
          "orders": [
            {
              "id": 1,
              "compagny": "ikea",
              "value": 5
            }
          ]
        }
      ],
      "id": 4
    },
    {
      "update": "2021-12-19T10:48:07.413Z",
      "data": [
        {
          "id": 1,
          "timestamp": 1639639519000,
          "expectedStock": 150,
          "realStock": 17,
          "orders": [
            {
              "id": 1,
              "compagny": "officeDepot",
              "value": 5
            },
            {
              "id": 2,
              "compagny": "mailChimp",
              "value": 3
            },
            {
              "id": 3,
              "compagny": "aliExpress",
              "value": 2
            },
            {
              "id": 4,
              "compagny": "delphiTools",
              "value": 7
            }
          ]
        },
        {
          "id": 2,
          "timestamp": 1639725919000,
          "expectedStock": 15,
          "realStock": 45,
          "orders": [
            {
              "id": 1,
              "compagny": "paper",
              "value": 5
            },
            {
              "id": 2,
              "compagny": "blue pens",
              "value": 5
            },
            {
              "id": 3,
              "compagny": "stapler",
              "value": 22
            },
            {
              "id": 3,
              "compagny": "post its",
              "value": 6
            },
            {
              "id": 4,
              "compagny": "calculator",
              "value": 7
            }
          ]
        },
        {
          "id": 3,
          "timestamp": 1639639519000,
          "expectedStock": 15,
          "realStock": 27,
          "orders": [
            {
              "id": 1,
              "compagny": "officeDepot",
              "value": 5
            },
            {
              "id": 2,
              "compagny": "officeDepot",
              "value": 5
            },
            {
              "id": 3,
              "compagny": "officeDepot",
              "value": 5
            },
            {
              "id": 4,
              "compagny": "mailChimp",
              "value": 3
            },
            {
              "id": 5,
              "compagny": "aliExpress",
              "value": 2
            },
            {
              "id": 6,
              "compagny": "delphiTools",
              "value": 7
            }
          ]
        },
        {
          "id": 4,
          "timestamp": 1639856376000,
          "expectedStock": 13,
          "realStock": 5,
          "orders": [
            {
              "id": 1,
              "compagny": "ikea",
              "value": 5
            }
          ]
        },
        {
          "id": 5,
          "timestamp": 1639639519000,
          "expectedStock": 15,
          "realStock": 17,
          "orders": [
            {
              "id": 1,
              "compagny": "officeDepot",
              "value": 5
            },
            {
              "id": 2,
              "compagny": "mailChimp",
              "value": 3
            },
            {
              "id": 3,
              "compagny": "aliExpress",
              "value": 2
            },
            {
              "id": 4,
              "compagny": "delphiTools",
              "value": 7
            }
          ]
        },
        {
          "id": 6,
          "timestamp": 1639725919000,
          "expectedStock": 13,
          "realStock": 12,
          "orders": [
            {
              "id": 1,
              "compagny": "ikea",
              "value": 5
            },
            {
              "id": 2,
              "compagny": "mailChimp",
              "value": 3
            },
            {
              "id": 3,
              "compagny": "aliExpress",
              "value": 4
            }
          ]
        },
        {
          "id": 7,
          "timestamp": 1639639519000,
          "expectedStock": 15,
          "realStock": 27,
          "orders": [
            {
              "id": 1,
              "compagny": "officeDepot",
              "value": 5
            },
            {
              "id": 2,
              "compagny": "officeDepot",
              "value": 5
            },
            {
              "id": 3,
              "compagny": "officeDepot",
              "value": 5
            },
            {
              "id": 4,
              "compagny": "mailChimp",
              "value": 3
            },
            {
              "id": 5,
              "compagny": "aliExpress",
              "value": 2
            },
            {
              "id": 6,
              "compagny": "delphiTools",
              "value": 7
            }
          ]
        },
        {
          "id": 8,
          "timestamp": 1639856376000,
          "expectedStock": 13,
          "realStock": 5,
          "orders": [
            {
              "id": 1,
              "compagny": "ikea",
              "value": 5
            }
          ]
        },
        {
          "id": 9,
          "timestamp": 1639639519000,
          "expectedStock": 15,
          "realStock": 17,
          "orders": [
            {
              "id": 1,
              "compagny": "officeDepot",
              "value": 5
            },
            {
              "id": 2,
              "compagny": "mailChimp",
              "value": 3
            },
            {
              "id": 3,
              "compagny": "aliExpress",
              "value": 2
            },
            {
              "id": 4,
              "compagny": "delphiTools",
              "value": 7
            }
          ]
        },
        {
          "id": 10,
          "timestamp": 1639725919000,
          "expectedStock": 13,
          "realStock": 12,
          "orders": [
            {
              "id": 1,
              "compagny": "ikea",
              "value": 5
            },
            {
              "id": 2,
              "compagny": "mailChimp",
              "value": 3
            },
            {
              "id": 3,
              "compagny": "aliExpress",
              "value": 4
            }
          ]
        },
        {
          "id": 11,
          "timestamp": 1639639519000,
          "expectedStock": 15,
          "realStock": 27,
          "orders": [
            {
              "id": 1,
              "compagny": "officeDepot",
              "value": 5
            },
            {
              "id": 2,
              "compagny": "officeDepot",
              "value": 5
            },
            {
              "id": 3,
              "compagny": "officeDepot",
              "value": 5
            },
            {
              "id": 4,
              "compagny": "mailChimp",
              "value": 3
            },
            {
              "id": 5,
              "compagny": "aliExpress",
              "value": 2
            },
            {
              "id": 6,
              "compagny": "delphiTools",
              "value": 7
            }
          ]
        },
        {
          "id": 12,
          "timestamp": 1639856376000,
          "expectedStock": 13,
          "realStock": 5,
          "orders": [
            {
              "id": 1,
              "compagny": "ikea",
              "value": 5
            }
          ]
        }
      ],
      "id": 5
    },
    {
      "update": "2021-12-19T19:53:20.980Z",
      "data": [
        {
          "id": 1,
          "timestamp": 1639639519000,
          "expectedStock": 150,
          "realStock": 170,
          "orders": [
            {
              "id": 1,
              "compagny": "officeDepot",
              "value": 50
            },
            {
              "id": 2,
              "compagny": "mailChimp",
              "value": 30
            },
            {
              "id": 3,
              "compagny": "aliExpress",
              "value": 20
            },
            {
              "id": 4,
              "compagny": "delphiTools",
              "value": 70
            }
          ]
        },
        {
          "id": 2,
          "timestamp": 1639725919000,
          "expectedStock": 130,
          "realStock": 175,
          "orders": [
            {
              "id": 1,
              "compagny": "paper",
              "value": 90
            },
            {
              "id": 2,
              "compagny": "blue pens",
              "value": 50
            },
            {
              "id": 3,
              "compagny": "stapler",
              "value": 22
            },
            {
              "id": 3,
              "compagny": "post its",
              "value": 6
            },
            {
              "id": 4,
              "compagny": "calculator",
              "value": 7
            }
          ]
        },
        {
          "id": 3,
          "timestamp": 1639639519000,
          "expectedStock": 120,
          "realStock": 117,
          "orders": [
            {
              "id": 1,
              "compagny": "officeDepot",
              "value": 5
            },
            {
              "id": 2,
              "compagny": "officeDepot",
              "value": 5
            },
            {
              "id": 3,
              "compagny": "officeDepot",
              "value": 50
            },
            {
              "id": 4,
              "compagny": "mailChimp",
              "value": 30
            },
            {
              "id": 5,
              "compagny": "aliExpress",
              "value": 20
            },
            {
              "id": 6,
              "compagny": "delphiTools",
              "value": 7
            }
          ]
        },
        {
          "id": 4,
          "timestamp": 1639856376000,
          "expectedStock": 110,
          "realStock": 115,
          "orders": [
            {
              "id": 1,
              "compagny": "ikea",
              "value": 115
            }
          ]
        },
        {
          "id": 5,
          "timestamp": 1639639519000,
          "expectedStock": 111,
          "realStock": 107,
          "orders": [
            {
              "id": 1,
              "compagny": "officeDepot",
              "value": 50
            },
            {
              "id": 2,
              "compagny": "mailChimp",
              "value": 30
            },
            {
              "id": 3,
              "compagny": "aliExpress",
              "value": 20
            },
            {
              "id": 4,
              "compagny": "delphiTools",
              "value": 7
            }
          ]
        },
        {
          "id": 6,
          "timestamp": 1639725919000,
          "expectedStock": 130,
          "realStock": 48,
          "orders": [
            {
              "id": 1,
              "compagny": "ikea",
              "value": 5
            },
            {
              "id": 2,
              "compagny": "mailChimp",
              "value": 3
            },
            {
              "id": 3,
              "compagny": "aliExpress",
              "value": 40
            }
          ]
        },
        {
          "id": 7,
          "timestamp": 1639639519000,
          "expectedStock": 140,
          "realStock": 99,
          "orders": [
            {
              "id": 1,
              "compagny": "officeDepot",
              "value": 5
            },
            {
              "id": 2,
              "compagny": "officeDepot",
              "value": 5
            },
            {
              "id": 3,
              "compagny": "officeDepot",
              "value": 50
            },
            {
              "id": 4,
              "compagny": "mailChimp",
              "value": 30
            },
            {
              "id": 5,
              "compagny": "aliExpress",
              "value": 2
            },
            {
              "id": 6,
              "compagny": "delphiTools",
              "value": 7
            }
          ]
        },
        {
          "id": 8,
          "timestamp": 1639856376000,
          "expectedStock": 150,
          "realStock": 140,
          "orders": [
            {
              "id": 1,
              "compagny": "ikea",
              "value": 140
            }
          ]
        },
        {
          "id": 9,
          "timestamp": 1639639519000,
          "expectedStock": 160,
          "realStock": 170,
          "orders": [
            {
              "id": 1,
              "compagny": "officeDepot",
              "value": 50
            },
            {
              "id": 2,
              "compagny": "mailChimp",
              "value": 30
            },
            {
              "id": 3,
              "compagny": "aliExpress",
              "value": 20
            },
            {
              "id": 4,
              "compagny": "delphiTools",
              "value": 70
            }
          ]
        },
        {
          "id": 10,
          "timestamp": 1639725919000,
          "expectedStock": 140,
          "realStock": 12,
          "orders": [
            {
              "id": 1,
              "compagny": "ikea",
              "value": 5
            },
            {
              "id": 2,
              "compagny": "mailChimp",
              "value": 3
            },
            {
              "id": 3,
              "compagny": "aliExpress",
              "value": 4
            }
          ]
        },
        {
          "id": 11,
          "timestamp": 1639639519000,
          "expectedStock": 150,
          "realStock": 145,
          "orders": [
            {
              "id": 1,
              "compagny": "officeDepot",
              "value": 5
            },
            {
              "id": 2,
              "compagny": "officeDepot",
              "value": 5
            },
            {
              "id": 3,
              "compagny": "officeDepot",
              "value": 5
            },
            {
              "id": 4,
              "compagny": "mailChimp",
              "value": 40
            },
            {
              "id": 5,
              "compagny": "aliExpress",
              "value": 20
            },
            {
              "id": 6,
              "compagny": "delphiTools",
              "value": 70
            }
          ]
        },
        {
          "id": 12,
          "timestamp": 1639856376000,
          "expectedStock": 130,
          "realStock": 135,
          "orders": [
            {
              "id": 1,
              "compagny": "ikea",
              "value": 135
            }
          ]
        }
      ],
      "id": 6
    }
  ]
}